{
  "price": 63.72,
  "drops": [
    {
      "skinName": "Slaughter",
      "skinWeapon": "Survival Knife",
      "skinPriceRange": "1260,27PLN",
      "skinDisplayChance": "0,052%",
      "skinImgSource": "https://cdn.key-drop.com/csgo_icons/63/6386e0fc798a1fa45acbb6fedb3bcb95.png",
      "skinRarity": "gold",
      "dropDetails": {
        "quality": "FN",
        "price": "1260,27PLN",
        "range": [
          99949,
          100000
        ],
        "odds": "0,052%"
      }
    },
    {
      "skinName": "Case Hardened",
      "skinWeapon": "Nomad Knife",
      "skinPriceRange": "1025,42PLN",
      "skinDisplayChance": "0,159%",
      "skinImgSource": "https://cdn.key-drop.com/csgo_icons/b3/b32a96bc2d1bb7bad4b8eb3a7ebcf38e.png",
      "skinRarity": "gold",
      "dropDetails": {
        "quality": "BS",
        "price": "1025,42PLN",
        "range": [
          99790,
          99948
        ],
        "odds": "0,159%"
      }
    },
    {
      "skinName": "Boreal Forest",
      "skinWeapon": "Nomad Knife",
      "skinPriceRange": "614,52PLN",
      "skinDisplayChance": "0,318%",
      "skinImgSource": "https://cdn.key-drop.com/csgo_icons/95/956c5bec29a8f1bcf23425ab800b7064.png",
      "skinRarity": "gold",
      "dropDetails": {
        "quality": "WW",
        "price": "614,52PLN",
        "range": [
          99472,
          99789
        ],
        "odds": "0,318%"
      }
    },
    {
      "skinName": "Hyper Beast",
      "skinWeapon": "M4A1-S",
      "skinPriceRange": "117,68PLN - 241,43PLN",
      "skinDisplayChance": "5,404%",
      "skinImgSource": "https://cdn.key-drop.com/csgo_icons/72/72cfe7b5eff4fcb227a87bdd60c8b142.png",
      "skinRarity": "red",
      "dropDetails": {
        "quality": "MW",
        "price": "241,43PLN",
        "range": [
          99362,
          99471
        ],
        "odds": "0,110%"
      }
    },
    {
      "skinName": "Hyper Beast",
      "skinWeapon": "M4A1-S",
      "skinPriceRange": "117,68PLN - 241,43PLN",
      "skinDisplayChance": "5,404%",
      "skinImgSource": "https://cdn.key-drop.com/csgo_icons/72/72cfe7b5eff4fcb227a87bdd60c8b142.png",
      "skinRarity": "red",
      "dropDetails": {
        "quality": "FT",
        "price": "117,68PLN",
        "range": [
          84075,
          89368
        ],
        "odds": "5,294%"
      }
    },
    {
      "skinName": "Golden Coil",
      "skinWeapon": "M4A1-S",
      "skinPriceRange": "128,30PLN - 231,44PLN",
      "skinDisplayChance": "1,658%",
      "skinImgSource": "https://cdn.key-drop.com/csgo_icons/d8/d81292a26bb03134e48364494ab932d1.png",
      "skinRarity": "red",
      "dropDetails": {
        "quality": "FT",
        "price": "231,44PLN",
        "range": [
          98528,
          99361
        ],
        "odds": "0,834%"
      }
    },
    {
      "skinName": "Golden Coil",
      "skinWeapon": "M4A1-S",
      "skinPriceRange": "128,30PLN - 231,44PLN",
      "skinDisplayChance": "1,658%",
      "skinImgSource": "https://cdn.key-drop.com/csgo_icons/d8/d81292a26bb03134e48364494ab932d1.png",
      "skinRarity": "red",
      "dropDetails": {
        "quality": "WW",
        "price": "181,26PLN",
        "range": [
          97788,
          98013
        ],
        "odds": "0,226%"
      }
    },
    {
      "skinName": "Golden Coil",
      "skinWeapon": "M4A1-S",
      "skinPriceRange": "128,30PLN - 231,44PLN",
      "skinDisplayChance": "1,658%",
      "skinImgSource": "https://cdn.key-drop.com/csgo_icons/d8/d81292a26bb03134e48364494ab932d1.png",
      "skinRarity": "red",
      "dropDetails": {
        "quality": "BS",
        "price": "128,30PLN",
        "range": [
          96157,
          96754
        ],
        "odds": "0,598%"
      }
    },
    {
      "skinName": "Containment Breach",
      "skinWeapon": "AWP",
      "skinPriceRange": "160,43PLN",
      "skinDisplayChance": "0,824%",
      "skinImgSource": "https://cdn.key-drop.com/csgo_icons/8d/8d4ac2729f9e7ec46bd29eb9785e2d29.png",
      "skinRarity": "red",
      "dropDetails": {
        "quality": "BS",
        "price": "160,43PLN",
        "range": [
          96964,
          97787
        ],
        "odds": "0,824%"
      }
    },
    {
      "skinName": "Hyper Beast",
      "skinWeapon": "Five-SeveN",
      "skinPriceRange": "67,46PLN - 140,85PLN",
      "skinDisplayChance": "0,341%",
      "skinImgSource": "https://cdn.key-drop.com/csgo_icons/b7/b705e07db1357302d11ee595ae5a9f20.png",
      "skinRarity": "red",
      "dropDetails": {
        "quality": "MW",
        "price": "140,85PLN",
        "range": [
          96755,
          96963
        ],
        "odds": "0,209%"
      }
    },
    {
      "skinName": "Hyper Beast",
      "skinWeapon": "Five-SeveN",
      "skinPriceRange": "67,46PLN - 140,85PLN",
      "skinDisplayChance": "0,341%",
      "skinImgSource": "https://cdn.key-drop.com/csgo_icons/b7/b705e07db1357302d11ee595ae5a9f20.png",
      "skinRarity": "red",
      "dropDetails": {
        "quality": "BS",
        "price": "67,46PLN",
        "range": [
          75897,
          76028
        ],
        "odds": "0,132%"
      }
    },
    {
      "skinName": "Hyper Beast",
      "skinWeapon": "AWP",
      "skinPriceRange": "125,64PLN",
      "skinDisplayChance": "4,765%",
      "skinImgSource": "https://cdn.key-drop.com/csgo_icons/29/2918085b1d0cf19e3f27f2a1586b5c72.png",
      "skinRarity": "red",
      "dropDetails": {
        "quality": "WW",
        "price": "125,64PLN",
        "range": [
          89369,
          94133
        ],
        "odds": "4,765%"
      }
    },
    {
      "skinName": "Neo-Noir",
      "skinWeapon": "AWP",
      "skinPriceRange": "120,78PLN",
      "skinDisplayChance": "1,727%",
      "skinImgSource": "https://cdn.key-drop.com/csgo_icons/d0/d0ed1c35d8364d8542e62f419c4c9985.png",
      "skinRarity": "red",
      "dropDetails": {
        "quality": "WW",
        "price": "120,78PLN",
        "range": [
          94134,
          95860
        ],
        "odds": "1,727%"
      }
    },
    {
      "skinName": "Neo-Noir",
      "skinWeapon": "USP-S",
      "skinPriceRange": "62,19PLN",
      "skinDisplayChance": "1,479%",
      "skinImgSource": "https://cdn.key-drop.com/csgo_icons/a5/a55499e3bd2ef59b732404e036a43388.png",
      "skinRarity": "red",
      "dropDetails": {
        "quality": "BS",
        "price": "62,19PLN",
        "range": [
          74418,
          75896
        ],
        "odds": "1,479%"
      }
    },
    {
      "skinName": "Stalker",
      "skinWeapon": "MAC-10",
      "skinPriceRange": "42,08PLN - 53,82PLN",
      "skinDisplayChance": "13,810%",
      "skinImgSource": "https://cdn.key-drop.com/csgo_icons/c1/c1a9d0f2e6edd7a4df7cf23b2a58a701.png",
      "skinRarity": "red",
      "dropDetails": {
        "quality": "FT",
        "price": "53,82PLN",
        "range": [
          67624,
          73384
        ],
        "odds": "5,761%"
      }
    },
    {
      "skinName": "Stalker",
      "skinWeapon": "MAC-10",
      "skinPriceRange": "42,08PLN - 53,82PLN",
      "skinDisplayChance": "13,810%",
      "skinImgSource": "https://cdn.key-drop.com/csgo_icons/c1/c1a9d0f2e6edd7a4df7cf23b2a58a701.png",
      "skinRarity": "red",
      "dropDetails": {
        "quality": "WW",
        "price": "47,57PLN",
        "range": [
          52998,
          57662
        ],
        "odds": "4,665%"
      }
    },
    {
      "skinName": "Stalker",
      "skinWeapon": "MAC-10",
      "skinPriceRange": "42,08PLN - 53,82PLN",
      "skinDisplayChance": "13,810%",
      "skinImgSource": "https://cdn.key-drop.com/csgo_icons/c1/c1a9d0f2e6edd7a4df7cf23b2a58a701.png",
      "skinRarity": "red",
      "dropDetails": {
        "quality": "BS",
        "price": "42,08PLN",
        "range": [
          49614,
          52997
        ],
        "odds": "3,384%"
      }
    },
    {
      "skinName": "The Emperor",
      "skinWeapon": "M4A4",
      "skinPriceRange": "38,75PLN - 47,88PLN",
      "skinDisplayChance": "12,637%",
      "skinImgSource": "https://cdn.key-drop.com/csgo_icons/3e/3ecc8d860236e73a561aef334dc3d404.png",
      "skinRarity": "red",
      "dropDetails": {
        "quality": "WW",
        "price": "47,88PLN",
        "range": [
          60365,
          65437
        ],
        "odds": "5,073%"
      }
    },
    {
      "skinName": "The Emperor",
      "skinWeapon": "M4A4",
      "skinPriceRange": "38,75PLN - 47,88PLN",
      "skinDisplayChance": "12,637%",
      "skinImgSource": "https://cdn.key-drop.com/csgo_icons/3e/3ecc8d860236e73a561aef334dc3d404.png",
      "skinRarity": "red",
      "dropDetails": {
        "quality": "FT",
        "price": "47,43PLN",
        "range": [
          57663,
          60364
        ],
        "odds": "2,702%"
      }
    },
    {
      "skinName": "The Emperor",
      "skinWeapon": "M4A4",
      "skinPriceRange": "38,75PLN - 47,88PLN",
      "skinDisplayChance": "12,637%",
      "skinImgSource": "https://cdn.key-drop.com/csgo_icons/3e/3ecc8d860236e73a561aef334dc3d404.png",
      "skinRarity": "red",
      "dropDetails": {
        "quality": "BS",
        "price": "38,75PLN",
        "range": [
          44752,
          49613
        ],
        "odds": "4,862%"
      }
    },
    {
      "skinName": "Neo-Noir",
      "skinWeapon": "M4A4",
      "skinPriceRange": "17,91PLN - 19,76PLN",
      "skinDisplayChance": "8,927%",
      "skinImgSource": "https://cdn.key-drop.com/csgo_icons/8c/8cc9ce7312dd5e7106ba40c0bf737ad6.png",
      "skinRarity": "red",
      "dropDetails": {
        "quality": "FT",
        "price": "19,76PLN",
        "range": [
          21007,
          24744
        ],
        "odds": "3,738%"
      }
    },
    {
      "skinName": "Neo-Noir",
      "skinWeapon": "M4A4",
      "skinPriceRange": "17,91PLN - 19,76PLN",
      "skinDisplayChance": "8,927%",
      "skinImgSource": "https://cdn.key-drop.com/csgo_icons/8c/8cc9ce7312dd5e7106ba40c0bf737ad6.png",
      "skinRarity": "red",
      "dropDetails": {
        "quality": "WW",
        "price": "17,91PLN",
        "range": [
          12034,
          17222
        ],
        "odds": "5,189%"
      }
    },
    {
      "skinName": "Cobalt Disruption",
      "skinWeapon": "Desert Eagle",
      "skinPriceRange": "215,15PLN",
      "skinDisplayChance": "0,514%",
      "skinImgSource": "https://cdn.key-drop.com/csgo_icons/58/58626738741232bd5b1cb44f7175ae59.png",
      "skinRarity": "pink",
      "dropDetails": {
        "quality": "MW",
        "price": "215,15PLN",
        "range": [
          98014,
          98527
        ],
        "odds": "0,514%"
      }
    },
    {
      "skinName": "Guardian",
      "skinWeapon": "M4A1-S",
      "skinPriceRange": "104,90PLN - 126,41PLN",
      "skinDisplayChance": "7,407%",
      "skinImgSource": "https://cdn.key-drop.com/csgo_icons/45/4512b1800d7d3081a876162df3dc8da8.png",
      "skinRarity": "pink",
      "dropDetails": {
        "quality": "MW",
        "price": "126,41PLN",
        "range": [
          95861,
          96156
        ],
        "odds": "0,296%"
      }
    },
    {
      "skinName": "Guardian",
      "skinWeapon": "M4A1-S",
      "skinPriceRange": "104,90PLN - 126,41PLN",
      "skinDisplayChance": "7,407%",
      "skinImgSource": "https://cdn.key-drop.com/csgo_icons/45/4512b1800d7d3081a876162df3dc8da8.png",
      "skinRarity": "pink",
      "dropDetails": {
        "quality": "FT",
        "price": "110,52PLN",
        "range": [
          81410,
          84074
        ],
        "odds": "2,665%"
      }
    },
    {
      "skinName": "Guardian",
      "skinWeapon": "M4A1-S",
      "skinPriceRange": "104,90PLN - 126,41PLN",
      "skinDisplayChance": "7,407%",
      "skinImgSource": "https://cdn.key-drop.com/csgo_icons/45/4512b1800d7d3081a876162df3dc8da8.png",
      "skinRarity": "pink",
      "dropDetails": {
        "quality": "WW",
        "price": "104,90PLN",
        "range": [
          76964,
          81409
        ],
        "odds": "4,446%"
      }
    },
    {
      "skinName": "Decimator",
      "skinWeapon": "Tec-9",
      "skinPriceRange": "39,83PLN - 73,40PLN",
      "skinDisplayChance": "5,301%",
      "skinImgSource": "https://cdn.key-drop.com/csgo_icons/7a/7a25771d889254ab2c71a11b9dc3a533.png",
      "skinRarity": "pink",
      "dropDetails": {
        "quality": "MW",
        "price": "73,40PLN",
        "range": [
          76029,
          76963
        ],
        "odds": "0,935%"
      }
    },
    {
      "skinName": "Decimator",
      "skinWeapon": "Tec-9",
      "skinPriceRange": "39,83PLN - 73,40PLN",
      "skinDisplayChance": "5,301%",
      "skinImgSource": "https://cdn.key-drop.com/csgo_icons/7a/7a25771d889254ab2c71a11b9dc3a533.png",
      "skinRarity": "pink",
      "dropDetails": {
        "quality": "FT",
        "price": "39,83PLN",
        "range": [
          40386,
          44751
        ],
        "odds": "4,366%"
      }
    },
    {
      "skinName": "Frontside Misty",
      "skinWeapon": "AK-47",
      "skinPriceRange": "65,16PLN",
      "skinDisplayChance": "1,033%",
      "skinImgSource": "https://cdn.key-drop.com/csgo_icons/9f/9f0f98e0a40c2a548519ecfaa202f7a0.png",
      "skinRarity": "pink",
      "dropDetails": {
        "quality": "WW",
        "price": "65,16PLN",
        "range": [
          73385,
          74417
        ],
        "odds": "1,033%"
      }
    },
    {
      "skinName": "Point Disarray",
      "skinWeapon": "AK-47",
      "skinPriceRange": "53,28PLN",
      "skinDisplayChance": "2,186%",
      "skinImgSource": "https://cdn.key-drop.com/csgo_icons/fa/fa6e9d8c067b42c8dca075bfa409db7e.png",
      "skinRarity": "pink",
      "dropDetails": {
        "quality": "FT",
        "price": "53,28PLN",
        "range": [
          65438,
          67623
        ],
        "odds": "2,186%"
      }
    },
    {
      "skinName": "Phosphor",
      "skinWeapon": "MP5-SD",
      "skinPriceRange": "25,11PLN - 36,00PLN",
      "skinDisplayChance": "7,033%",
      "skinImgSource": "https://cdn.key-drop.com/csgo_icons/69/693e76619df8ec29cf358d70b9f10297.png",
      "skinRarity": "pink",
      "dropDetails": {
        "quality": "FN",
        "price": "36,00PLN",
        "range": [
          36657,
          40385
        ],
        "odds": "3,729%"
      }
    },
    {
      "skinName": "Phosphor",
      "skinWeapon": "MP5-SD",
      "skinPriceRange": "25,11PLN - 36,00PLN",
      "skinDisplayChance": "7,033%",
      "skinImgSource": "https://cdn.key-drop.com/csgo_icons/69/693e76619df8ec29cf358d70b9f10297.png",
      "skinRarity": "pink",
      "dropDetails": {
        "quality": "MW",
        "price": "25,11PLN",
        "range": [
          24745,
          28048
        ],
        "odds": "3,304%"
      }
    },
    {
      "skinName": "Bloodshot",
      "skinWeapon": "SSG 08",
      "skinPriceRange": "32,58PLN - 33,98PLN",
      "skinDisplayChance": "5,952%",
      "skinImgSource": "https://cdn.key-drop.com/csgo_icons/7f/7f3cb831b0c380ce67e0d6f0edff15aa.png",
      "skinRarity": "pink",
      "dropDetails": {
        "quality": "FT",
        "price": "33,98PLN",
        "range": [
          31013,
          34000
        ],
        "odds": "2,988%"
      }
    },
    {
      "skinName": "Bloodshot",
      "skinWeapon": "SSG 08",
      "skinPriceRange": "32,58PLN - 33,98PLN",
      "skinDisplayChance": "5,952%",
      "skinImgSource": "https://cdn.key-drop.com/csgo_icons/7f/7f3cb831b0c380ce67e0d6f0edff15aa.png",
      "skinRarity": "pink",
      "dropDetails": {
        "quality": "WW",
        "price": "32,58PLN",
        "range": [
          28049,
          31012
        ],
        "odds": "2,964%"
      }
    },
    {
      "skinName": "Wasteland Princess",
      "skinWeapon": "Sawed-Off",
      "skinPriceRange": "16,43PLN - 33,53PLN",
      "skinDisplayChance": "6,742%",
      "skinImgSource": "https://cdn.key-drop.com/csgo_icons/bb/bbb754e65485c9ce375dd1aff92f33c2.png",
      "skinRarity": "pink",
      "dropDetails": {
        "quality": "FN",
        "price": "33,53PLN",
        "range": [
          34001,
          36656
        ],
        "odds": "2,656%"
      }
    },
    {
      "skinName": "Wasteland Princess",
      "skinWeapon": "Sawed-Off",
      "skinPriceRange": "16,43PLN - 33,53PLN",
      "skinDisplayChance": "6,742%",
      "skinImgSource": "https://cdn.key-drop.com/csgo_icons/bb/bbb754e65485c9ce375dd1aff92f33c2.png",
      "skinRarity": "pink",
      "dropDetails": {
        "quality": "MW",
        "price": "16,43PLN",
        "range": [
          7948,
          12033
        ],
        "odds": "4,086%"
      }
    },
    {
      "skinName": "Desolate Space",
      "skinWeapon": "M4A4",
      "skinPriceRange": "15,44PLN - 17,33PLN",
      "skinDisplayChance": "11,731%",
      "skinImgSource": "https://cdn.key-drop.com/csgo_icons/4b/4bfee5381c335a970a77254d952c1f3f.png",
      "skinRarity": "pink",
      "dropDetails": {
        "quality": "FT",
        "price": "17,33PLN",
        "range": [
          17223,
          21006
        ],
        "odds": "3,784%"
      }
    },
    {
      "skinName": "Desolate Space",
      "skinWeapon": "M4A4",
      "skinPriceRange": "15,44PLN - 17,33PLN",
      "skinDisplayChance": "11,731%",
      "skinImgSource": "https://cdn.key-drop.com/csgo_icons/4b/4bfee5381c335a970a77254d952c1f3f.png",
      "skinRarity": "pink",
      "dropDetails": {
        "quality": "WW",
        "price": "15,89PLN",
        "range": [
          3251,
          7947
        ],
        "odds": "4,697%"
      }
    },
    {
      "skinName": "Desolate Space",
      "skinWeapon": "M4A4",
      "skinPriceRange": "15,44PLN - 17,33PLN",
      "skinDisplayChance": "11,731%",
      "skinImgSource": "https://cdn.key-drop.com/csgo_icons/4b/4bfee5381c335a970a77254d952c1f3f.png",
      "skinRarity": "pink",
      "dropDetails": {
        "quality": "BS",
        "price": "15,44PLN",
        "range": [
          1,
          3250
        ],
        "odds": "3,250%"
      }
    }
  ]
}